LogXML2Chunks/LogXML2Chunks.py
LogXML2Chunks/__init__.py
LogXML2Chunks/cli.py
robotframework_logxml2chunks-1.1.0.dist-info/licenses/LICENSE
robotframework_logxml2chunks-1.1.0.dist-info/METADATA
robotframework_logxml2chunks-1.1.0.dist-info/WHEEL
robotframework_logxml2chunks-1.1.0.dist-info/entry_points.txt
robotframework_logxml2chunks-1.1.0.dist-info/top_level.txt
robotframework_logxml2chunks-1.1.0.dist-info/RECORD
